{"ranking":[{"name":"Afghanistan","value":63961},{"name":"Albania","value":29200},{"name":"Algeria","value":86666},{"name":"Andorra","value":15050},{"name":"Angola","value":58044},{"name":"Argentina","value":180708},{"name":"Armenia","value":107611},{"name":"Australia","value":389046},{"name":"Austria","value":343258},{"name":"Azerbaijan","value":78437},{"name":"Bahrain","value":32536},{"name":"Bangladesh","value":217431},{"name":"Belarus","value":79428},{"name":"Belgium","value":339690},{"name":"Benin","value":47988},{"name":"Bhutan","value":14324},{"name":"Bolivia","value":93373},{"name":"Bosnia and Herz.","value":154},{"name":"Botswana","value":21229},{"name":"Brazil","value":238257},{"name":"Bulgaria","value":180375},{"name":"Burkina Faso","value":10110},{"name":"Burundi","value":18765},{"name":"Cambodia","value":92795},{"name":"Cameroon","value":120977},{"name":"Canada","value":415700},{"name":"Chad","value":5916},{"name":"Chile","value":139399},{"name":"China","value":365399},{"name":"Colombia","value":162208},{"name":"Congo","value":28164},{"name":"Croatia","value":137979},{"name":"Cuba","value":73971},{"name":"Cyprus","value":84669},{"name":"Czechia","value":315674},{"name":"Denmark","value":277878},{"name":"Dominican Rep.","value":38647},{"name":"Ecuador","value":89434},{"name":"Egypt","value":174713},{"name":"El Salvador","value":51963},{"name":"Estonia","value":136373},{"name":"Ethiopia","value":207172},{"name":"Finland","value":264903},{"name":"France","value":548028},{"name":"Georgia","value":140006},{"name":"Germany","value":597226},{"name":"Ghana","value":158476},{"name":"Greece","value":182272},{"name":"Guatemala","value":78381},{"name":"Honduras","value":40716},{"name":"Hong Kong","value":194161},{"name":"Hungary","value":189669},{"name":"Iceland","value":58572},{"name":"India","value":246134},{"name":"Indonesia","value":377323},{"name":"Iran","value":201461},{"name":"Iraq","value":50667},{"name":"Ireland","value":200030},{"name":"Israel","value":211954},{"name":"Italy","value":357726},{"name":"Jamaica","value":68533},{"name":"Japan","value":589509},{"name":"Jordan","value":71281},{"name":"Kazakhstan","value":78644},{"name":"Kenya","value":285543},{"name":"Kuwait","value":22752},{"name":"Laos","value":11106},{"name":"Latvia","value":75848},{"name":"Lithuania","value":83263},{"name":"Luxembourg","value":77041},{"name":"Madagascar","value":124143},{"name":"Malawi","value":40508},{"name":"Malaysia","value":150580},{"name":"Maldives","value":14472},{"name":"Mali","value":12081},{"name":"Malta","value":38939},{"name":"Mauritania","value":8754},{"name":"Mauritius","value":30690},{"name":"Mexico","value":160793},{"name":"Moldova","value":62177},{"name":"Mongolia","value":46586},{"name":"Montenegro","value":45648},{"name":"Morocco","value":151753},{"name":"Mozambique","value":34860},{"name":"Myanmar","value":88364},{"name":"Namibia","value":12765},{"name":"Nepal","value":161550},{"name":"Netherlands","value":451782},{"name":"New Zealand","value":154539},{"name":"Nicaragua","value":103992},{"name":"Nigeria","value":165007},{"name":"Norway","value":265680},{"name":"Oman","value":59488},{"name":"Pakistan","value":192199},{"name":"Palestine","value":79106},{"name":"Panama","value":33585},{"name":"Paraguay","value":68456},{"name":"Peru","value":92268},{"name":"Philippines","value":291455},{"name":"Poland","value":390999},{"name":"Portugal","value":247078},{"name":"Qatar","value":34537},{"name":"Romania","value":200489},{"name":"Russia","value":210506},{"name":"Rwanda","value":195115},{"name":"San Marino","value":3527},{"name":"Saudi Arabia","value":48285},{"name":"Senegal","value":56654},{"name":"Serbia","value":137212},{"name":"Sierra Leone","value":8017},{"name":"Singapore","value":216973},{"name":"Slovakia","value":100362},{"name":"Slovenia","value":104085},{"name":"South Africa","value":130247},{"name":"South Korea","value":258661},{"name":"Spain","value":379589},{"name":"Sri Lanka","value":207677},{"name":"Sudan","value":26584},{"name":"Sweden","value":327262},{"name":"Switzerland","value":417168},{"name":"Syria","value":54165},{"name":"Taiwan","value":344156},{"name":"Tanzania","value":94708},{"name":"Thailand","value":223694},{"name":"Tunisia","value":115103},{"name":"Turkey","value":179910},{"name":"Uganda","value":135126},{"name":"Ukraine","value":197462},{"name":"United Arab Emirates","value":288},{"name":"United Kingdom","value":444868},{"name":"United States of America","value":408698},{"name":"Uruguay","value":83809},{"name":"Uzbekistan","value":130068},{"name":"Venezuela","value":111835},{"name":"Vietnam","value":261482},{"name":"Yemen","value":62473},{"name":"Zambia","value":40242},{"name":"Zambia","value":85772}]}
