{"ranking":[{"name":"Afghanistan","value":63703},{"name":"Albania","value":29367},{"name":"Algeria","value":88379},{"name":"Andorra","value":14741},{"name":"Angola","value":57555},{"name":"Argentina","value":182571},{"name":"Armenia","value":109175},{"name":"Australia","value":392002},{"name":"Austria","value":342106},{"name":"Azerbaijan","value":87660},{"name":"Bahrain","value":33133},{"name":"Bangladesh","value":219457},{"name":"Belarus","value":86965},{"name":"Belgium","value":336609},{"name":"Benin","value":49798},{"name":"Bhutan","value":14317},{"name":"Bolivia","value":96732},{"name":"Bosnia and Herz.","value":146},{"name":"Botswana","value":22716},{"name":"Brazil","value":238257},{"name":"Bulgaria","value":178268},{"name":"Burkina Faso","value":10341},{"name":"Burundi","value":18270},{"name":"Cambodia","value":91830},{"name":"Cameroon","value":120421},{"name":"Canada","value":419741},{"name":"Chad","value":5960},{"name":"Chile","value":140195},{"name":"China","value":365736},{"name":"Colombia","value":164161},{"name":"Congo","value":28164},{"name":"Croatia","value":134548},{"name":"Cuba","value":73296},{"name":"Cyprus","value":89177},{"name":"Czechia","value":323323},{"name":"Denmark","value":291537},{"name":"Dominican Rep.","value":39308},{"name":"Ecuador","value":92506},{"name":"Egypt","value":172571},{"name":"El Salvador","value":52378},{"name":"Estonia","value":137209},{"name":"Ethiopia","value":207616},{"name":"Finland","value":267881},{"name":"France","value":548192},{"name":"Georgia","value":138503},{"name":"Germany","value":610477},{"name":"Ghana","value":156556},{"name":"Greece","value":184453},{"name":"Guatemala","value":77053},{"name":"Honduras","value":37757},{"name":"Hong Kong","value":195076},{"name":"Hungary","value":186487},{"name":"Iceland","value":57492},{"name":"India","value":238931},{"name":"Indonesia","value":364811},{"name":"Iran","value":195905},{"name":"Iraq","value":50172},{"name":"Ireland","value":202872},{"name":"Israel","value":208981},{"name":"Italy","value":366378},{"name":"Jamaica","value":67458},{"name":"Japan","value":602981},{"name":"Jordan","value":71893},{"name":"Kazakhstan","value":78309},{"name":"Kenya","value":280350},{"name":"Kuwait","value":23227},{"name":"Laos","value":11438},{"name":"Latvia","value":87708},{"name":"Lithuania","value":83263},{"name":"Luxembourg","value":78786},{"name":"Madagascar","value":123505},{"name":"Malawi","value":40841},{"name":"Malaysia","value":152638},{"name":"Maldives","value":12990},{"name":"Mali","value":12715},{"name":"Malta","value":39558},{"name":"Mauritania","value":8701},{"name":"Mauritius","value":31802},{"name":"Mexico","value":164773},{"name":"Moldova","value":62376},{"name":"Mongolia","value":47101},{"name":"Montenegro","value":45210},{"name":"Morocco","value":152314},{"name":"Mozambique","value":33892},{"name":"Myanmar","value":86958},{"name":"Namibia","value":13137},{"name":"Nepal","value":161650},{"name":"Netherlands","value":448528},{"name":"New Zealand","value":155275},{"name":"Nicaragua","value":101935},{"name":"Nigeria","value":166385},{"name":"Norway","value":273815},{"name":"Oman","value":59649},{"name":"Pakistan","value":193075},{"name":"Palestine","value":77185},{"name":"Panama","value":32944},{"name":"Paraguay","value":70456},{"name":"Peru","value":92794},{"name":"Philippines","value":288149},{"name":"Poland","value":385722},{"name":"Portugal","value":248060},{"name":"Qatar","value":36164},{"name":"Romania","value":200685},{"name":"Russia","value":205262},{"name":"Rwanda","value":203297},{"name":"San Marino","value":3447},{"name":"Saudi Arabia","value":48669},{"name":"Senegal","value":55375},{"name":"Serbia","value":145644},{"name":"Sierra Leone","value":8282},{"name":"Singapore","value":215114},{"name":"Slovakia","value":100931},{"name":"Slovenia","value":105452},{"name":"South Africa","value":132383},{"name":"South Korea","value":258780},{"name":"Spain","value":384629},{"name":"Sri Lanka","value":203688},{"name":"Sudan","value":27664},{"name":"Sweden","value":330540},{"name":"Switzerland","value":417905},{"name":"Syria","value":54616},{"name":"Taiwan","value":346177},{"name":"Tanzania","value":93582},{"name":"Thailand","value":224975},{"name":"Tunisia","value":116867},{"name":"Turkey","value":179993},{"name":"Uganda","value":137161},{"name":"Ukraine","value":198293},{"name":"United Arab Emirates","value":299},{"name":"United Kingdom","value":441095},{"name":"United States of America","value":442552},{"name":"Uruguay","value":83623},{"name":"Uzbekistan","value":130315},{"name":"Venezuela","value":106703},{"name":"Vietnam","value":257770},{"name":"Yemen","value":63198},{"name":"Zambia","value":42068},{"name":"Zambia","value":88960}]}
